merhaba_dunya/__init__.py
merhaba_dunya/merhaba.py
merhaba_dunya/yardimcilar.py
merhaba_dunya-0.1.0.dist-info/licenses/LICENSE
merhaba_dunya-0.1.0.dist-info/METADATA
merhaba_dunya-0.1.0.dist-info/WHEEL
merhaba_dunya-0.1.0.dist-info/top_level.txt
merhaba_dunya-0.1.0.dist-info/RECORD
