Metadata-Version: 2.4
Name: merhaba-dunya
Version: 0.1.0
Summary: Basit bir merhaba dünya paketi
Home-page: https://github.com/aribilgiogr/merhaba-dunya
Author: Arı Bilgi Ogr
Author-email: aribilgiogr@gmail.com
Classifier: Programming Language :: Python :: 3
Classifier: License :: OSI Approved :: MIT License
Classifier: Operating System :: OS Independent
Requires-Python: >=3.7
License-File: LICENSE
Dynamic: author
Dynamic: author-email
Dynamic: classifier
Dynamic: description
Dynamic: description-content-type
Dynamic: home-page
Dynamic: license-file
Dynamic: requires-python
Dynamic: summary
